tacco/__init__.py
tacco/benchmarking/__init__.py
tacco/benchmarking/_benchmarking.py
tacco/eval/__init__.py
tacco/eval/score_error.py
tacco/get/__init__.py
tacco/get/_counts.py
tacco/get/_data.py
tacco/get/_positions.py
tacco/plots/__init__.py
tacco/plots/_plots.py
tacco/preprocessing/__init__.py
tacco/preprocessing/_platform.py
tacco/preprocessing/_qc.py
tacco/preprocessing/_reference.py
tacco/testing/__init__.py
tacco/testing/_assert.py
tacco/testing/_freeze.py
tacco/tools/_NMFreg.py
tacco/tools/_OT.py
tacco/tools/_RCTD.py
tacco/tools/_SingleR.py
tacco/tools/__init__.py
tacco/tools/_annotate.py
tacco/tools/_co_occurrence.py
tacco/tools/_enrichments.py
tacco/tools/_find_regions.py
tacco/tools/_goa.py
tacco/tools/_helper.py
tacco/tools/_in_silico.py
tacco/tools/_nnls.py
tacco/tools/_novosparc.py
tacco/tools/_orthology.py
tacco/tools/_points.py
tacco/tools/_projection.py
tacco/tools/_split.py
tacco/tools/_svm.py
tacco/tools/_tangram.py
tacco/tools/_wot.py
tacco/utils/__init__.py
tacco/utils/_dist.py
tacco/utils/_mannwhitneyu.py
tacco/utils/_math.py
tacco/utils/_points.py
tacco/utils/_split.py
tacco/utils/_stats.py
tacco/utils/_utils.py
tacco-0.4.0.post1.dist-info/LICENCE.txt
tacco-0.4.0.post1.dist-info/METADATA
tacco-0.4.0.post1.dist-info/NOTICE.md
tacco-0.4.0.post1.dist-info/WHEEL
tacco-0.4.0.post1.dist-info/top_level.txt
tacco-0.4.0.post1.dist-info/RECORD
