Metadata-Version: 2.1
Name: tacco
Version: 0.4.0.post1
Summary: TACCO: Transfer of Annotations to Cells and their COmbinations
Author: Simon Mages, Noa Moriel, Jan Watter
Maintainer-email: Jan Watter <jan.watter@gmail.com>, Simon Mages <smages@broadinstitute.org>
License: BSD 3-Clause License
Project-URL: Source, https://github.com/simonwm/tacco
Project-URL: Documentation, https://simonwm.github.io/tacco/index.html
Classifier: License :: OSI Approved :: BSD License
Classifier: Intended Audience :: Developers
Classifier: Intended Audience :: Science/Research
Classifier: Natural Language :: English
Classifier: Programming Language :: Python :: 3
Classifier: Operating System :: OS Independent
Classifier: Topic :: Scientific/Engineering :: Bio-Informatics
Classifier: Topic :: Scientific/Engineering :: Visualization
Requires-Python: >=3.7
License-File: LICENCE.txt
License-File: NOTICE.md
Requires-Dist: requests
Requires-Dist: joblib
Requires-Dist: numba >=0.51.2
Requires-Dist: numpy
Requires-Dist: matplotlib !=3.7
Requires-Dist: seaborn
Requires-Dist: sparse-dot-mkl >=0.7.3
Requires-Dist: scanpy >=1.7.0
Requires-Dist: statsmodels
Requires-Dist: anndata >=0.9.0
Requires-Dist: pandas >=1.1.0
Requires-Dist: scipy >=1.6.0
Requires-Dist: mkl
Requires-Dist: mkl-service
Requires-Dist: scikit-learn
Requires-Dist: threadpoolctl
Requires-Dist: pyamg
Provides-Extra: benchmark
Requires-Dist: time ; extra == 'benchmark'
Provides-Extra: doc
Requires-Dist: sphinx ; extra == 'doc'
Requires-Dist: sphinx-rtd-theme ; extra == 'doc'
Requires-Dist: pydata-sphinx-theme ; extra == 'doc'
Requires-Dist: sphinx-autodoc-typehints ; extra == 'doc'
Requires-Dist: nbsphinx ; extra == 'doc'
Requires-Dist: ipython ; extra == 'doc'
Requires-Dist: jupytext ; extra == 'doc'
Requires-Dist: jupyter ; extra == 'doc'
Provides-Extra: test
Requires-Dist: pytest ; extra == 'test'
